yamlpath/__init__.py
yamlpath/func.py
yamlpath/processor.py
yamlpath/yamlpath.py
yamlpath/commands/__init__.py
yamlpath/commands/eyaml_rotate_keys.py
yamlpath/commands/yaml_diff.py
yamlpath/commands/yaml_get.py
yamlpath/commands/yaml_merge.py
yamlpath/commands/yaml_paths.py
yamlpath/commands/yaml_set.py
yamlpath/commands/yaml_validate.py
yamlpath/common/__init__.py
yamlpath/common/anchors.py
yamlpath/common/keywordsearches.py
yamlpath/common/nodes.py
yamlpath/common/parsers.py
yamlpath/common/searches.py
yamlpath/differ/__init__.py
yamlpath/differ/diffentry.py
yamlpath/differ/differ.py
yamlpath/differ/differconfig.py
yamlpath/differ/enums/__init__.py
yamlpath/differ/enums/aohdiffopts.py
yamlpath/differ/enums/arraydiffopts.py
yamlpath/differ/enums/diffactions.py
yamlpath/enums/__init__.py
yamlpath/enums/anchormatches.py
yamlpath/enums/collectoroperators.py
yamlpath/enums/includealiases.py
yamlpath/enums/pathsearchkeywords.py
yamlpath/enums/pathsearchmethods.py
yamlpath/enums/pathsegmenttypes.py
yamlpath/enums/pathseparators.py
yamlpath/enums/pathseperators.py
yamlpath/enums/yamlvalueformats.py
yamlpath/exceptions/__init__.py
yamlpath/exceptions/badaliasyamlpathexception.py
yamlpath/exceptions/duplicatekeyyamlpathexception.py
yamlpath/exceptions/nodocumentyamlpathexception.py
yamlpath/exceptions/recursionyamlpathexception.py
yamlpath/exceptions/typemismatchyamlpathexception.py
yamlpath/exceptions/unmatchedyamlpathexception.py
yamlpath/exceptions/yamlpathexception.py
yamlpath/eyaml/__init__.py
yamlpath/eyaml/eyamlprocessor.py
yamlpath/eyaml/enums/__init__.py
yamlpath/eyaml/enums/eyamloutputformats.py
yamlpath/eyaml/exceptions/__init__.py
yamlpath/eyaml/exceptions/eyamlcommand.py
yamlpath/merger/__init__.py
yamlpath/merger/merger.py
yamlpath/merger/mergerconfig.py
yamlpath/merger/enums/__init__.py
yamlpath/merger/enums/anchorconflictresolutions.py
yamlpath/merger/enums/aohmergeopts.py
yamlpath/merger/enums/arraymergeopts.py
yamlpath/merger/enums/hashmergeopts.py
yamlpath-3.8.1.dist-info/LICENSE
yamlpath-3.8.1.dist-info/METADATA
yamlpath-3.8.1.dist-info/WHEEL
yamlpath-3.8.1.dist-info/entry_points.txt
yamlpath-3.8.1.dist-info/top_level.txt
yamlpath-3.8.1.dist-info/RECORD
