Metadata-Version: 2.1
Name: yamlpath
Version: 3.8.1
Summary: Command-line get/set/merge/validate/scan/convert/diff processors for YAML/JSON/Compatible data using powerful, intuitive, command-line friendly syntax
Home-page: https://github.com/wwkimball/yamlpath
Author: William W. Kimball, Jr., MBA, MSIS
Author-email: github-yamlpath@kimballstuff.com
License: ISC
Keywords: yaml eyaml json yaml-path diff merge
Classifier: Development Status :: 5 - Production/Stable
Classifier: License :: OSI Approved :: ISC License (ISCL)
Classifier: Programming Language :: Python :: 3.6
Classifier: Programming Language :: Python :: 3.7
Classifier: Programming Language :: Python :: 3.8
Classifier: Programming Language :: Python :: 3.9
Classifier: Programming Language :: Python :: 3.10
Classifier: Programming Language :: Python :: 3.11
Classifier: Operating System :: OS Independent
Classifier: Environment :: Console
Classifier: Topic :: Utilities
Classifier: Topic :: Software Development :: Libraries :: Python Modules
Requires-Python: >3.6.0
License-File: LICENSE
Requires-Dist: ruamel.yaml !=0.17.18,<=0.17.21,>0.17.5
Requires-Dist: python-dateutil <=3
